django_sharepoint_storage/SharePointClients.py
django_sharepoint_storage/SharePointCloudStorageUtils.py
django_sharepoint_storage/SharePointFile.py
django_sharepoint_storage/SharePointStorage.py
django_sharepoint_storage/__init__.py
DjangoSharepointStorage-1.0.0.dist-info/LICENSE.txt
DjangoSharepointStorage-1.0.0.dist-info/METADATA
DjangoSharepointStorage-1.0.0.dist-info/WHEEL
DjangoSharepointStorage-1.0.0.dist-info/top_level.txt
DjangoSharepointStorage-1.0.0.dist-info/RECORD
